<?xml version="1.0" encoding="UTF-8"?><record_update table="sys_app_scan_variable">
    <sys_app_scan_variable action="DELETE">
        <name>sys_id_12144</name>
        <original_value>bd6cacf1df5b56103c3fefbdae2603b9</original_value>
        <referenced_table>sys_app</referenced_table>
        <run_script>false</run_script>
        <scan_instance>5a842a9f5d1b5a10aa5e27a08e4bccd4</scan_instance>
        <scan_source>scan</scan_source>
        <source_id>a3a29f2afbed9a90c04cfbac7befdc25</source_id>
        <sys_class_name>sys_app_scan_variable</sys_class_name>
        <sys_created_by>john.spirko</sys_created_by>
        <sys_created_on>2025-01-30 04:29:43</sys_created_on>
        <sys_id>0746ea5b755b5a1045ce43a48beaabb3</sys_id>
        <sys_mod_count>0</sys_mod_count>
        <sys_name>sys_id_12144</sys_name>
        <sys_package display_value="Social Program Support - Pub Sector" source="x_snc_hhs_progra_2">acb2df2afbed9a90c04cfbac7befdc2e</sys_package>
        <sys_policy/>
        <sys_scope display_value="Social Program Support - Pub Sector">acb2df2afbed9a90c04cfbac7befdc2e</sys_scope>
        <sys_update_name>sys_app_scan_variable_0746ea5b755b5a1045ce43a48beaabb3</sys_update_name>
        <sys_updated_by>john.spirko</sys_updated_by>
        <sys_updated_on>2025-01-30 04:29:43</sys_updated_on>
        <template_execution_script/>
        <type display_value="Reference">242d82a65bea101001fb0c370581c7ea</type>
        <variable_hash>3067271dfe1b92e3539773d69624798b48ef82035e2d1133130cf1a37747cbd3</variable_hash>
    </sys_app_scan_variable>
    <sys_update_version action="INSERT_OR_UPDATE">
        <action>DELETE</action>
        <application display_value="Social Program Support - Pub Sector">acb2df2afbed9a90c04cfbac7befdc2e</application>
        <file_path/>
        <instance_id>efeaa946dbc0c740b2e05d00cf96194a</instance_id>
        <instance_name>empjspirkosc2</instance_name>
        <name>sys_app_scan_variable_0746ea5b755b5a1045ce43a48beaabb3</name>
        <payload><![CDATA[<?xml version="1.0" encoding="UTF-8"?><record_update table="sys_app_scan_variable"><sys_app_scan_variable action="INSERT_OR_UPDATE"><name>sys_id_12144</name><original_value>bd6cacf1df5b56103c3fefbdae2603b9</original_value><referenced_table>sys_app</referenced_table><run_script>false</run_script><scan_instance>5a842a9f5d1b5a10aa5e27a08e4bccd4</scan_instance><scan_source>scan</scan_source><source_id>a3a29f2afbed9a90c04cfbac7befdc25</source_id><sys_class_name>sys_app_scan_variable</sys_class_name><sys_created_by>john.spirko</sys_created_by><sys_created_on>2025-01-30 04:29:43</sys_created_on><sys_id>0746ea5b755b5a1045ce43a48beaabb3</sys_id><sys_mod_count>0</sys_mod_count><sys_name>sys_id_12144</sys_name><sys_package display_value="Social Program Support - Pub Sector" source="x_snc_hhs_progra_2">acb2df2afbed9a90c04cfbac7befdc2e</sys_package><sys_policy/><sys_scope display_value="Social Program Support - Pub Sector">acb2df2afbed9a90c04cfbac7befdc2e</sys_scope><sys_update_name>sys_app_scan_variable_0746ea5b755b5a1045ce43a48beaabb3</sys_update_name><sys_updated_by>john.spirko</sys_updated_by><sys_updated_on>2025-01-30 04:29:43</sys_updated_on><template_execution_script/><type display_value="Reference">242d82a65bea101001fb0c370581c7ea</type><variable_hash>3067271dfe1b92e3539773d69624798b48ef82035e2d1133130cf1a37747cbd3</variable_hash></sys_app_scan_variable></record_update>]]></payload>
        <payload_hash>586878631</payload_hash>
        <record_name>sys_id_12144</record_name>
        <reverted_from/>
        <source>8a9481db93ad9e90d6aabe8d1dba103a</source>
        <source_table>sys_update_set</source_table>
        <state>previous</state>
        <sys_created_by>john.spirko</sys_created_by>
        <sys_created_on>2025-01-30 04:29:43</sys_created_on>
        <sys_id>8346ea5bfb5b5a10625bf7704eefdcb5</sys_id>
        <sys_mod_count>0</sys_mod_count>
        <sys_recorded_at>194b578d87e0000001</sys_recorded_at>
        <sys_updated_by>john.spirko</sys_updated_by>
        <sys_updated_on>2025-01-30 04:29:43</sys_updated_on>
        <type>Variable</type>
        <update_guid>4746ea5bd05b5a10bc2b2ba064d9b6b4</update_guid>
        <update_guid_history>4746ea5bd05b5a10bc2b2ba064d9b6b4:586878631</update_guid_history>
    </sys_update_version>
    <sys_metadata_delete action="INSERT_OR_UPDATE">
        <sys_audit_delete/>
        <sys_class_name>sys_metadata_delete</sys_class_name>
        <sys_created_by>john.spirko</sys_created_by>
        <sys_created_on>2025-01-30 05:10:10</sys_created_on>
        <sys_db_object display_value="" name="sys_app_scan_variable">sys_app_scan_variable</sys_db_object>
        <sys_id>15d2cd7ce01f43d8974ffdb6ea174364</sys_id>
        <sys_metadata>0746ea5b755b5a1045ce43a48beaabb3</sys_metadata>
        <sys_mod_count>0</sys_mod_count>
        <sys_name>sys_id_12144</sys_name>
        <sys_package display_value="Social Program Support - Pub Sector" source="x_snc_hhs_progra_2">acb2df2afbed9a90c04cfbac7befdc2e</sys_package>
        <sys_parent/>
        <sys_policy/>
        <sys_scope display_value="Social Program Support - Pub Sector">acb2df2afbed9a90c04cfbac7befdc2e</sys_scope>
        <sys_scope_delete display_value="">3193c3af00d14183a2bae770b8670da1</sys_scope_delete>
        <sys_update_name>sys_app_scan_variable_0746ea5b755b5a1045ce43a48beaabb3</sys_update_name>
        <sys_update_version display_value="sys_app_scan_variable_0746ea5b755b5a1045ce43a48beaabb3">8346ea5bfb5b5a10625bf7704eefdcb5</sys_update_version>
        <sys_updated_by>john.spirko</sys_updated_by>
        <sys_updated_on>2025-01-30 05:10:10</sys_updated_on>
    </sys_metadata_delete>
</record_update>
