<?xml version="1.0" encoding="UTF-8"?><record_update table="sys_app_scan_variable">
    <sys_app_scan_variable action="DELETE">
        <name>sys_id_5025</name>
        <original_value>cca1a2c33ccfd65040144ff95a45d483</original_value>
        <referenced_table>sys_app</referenced_table>
        <run_script>false</run_script>
        <scan_instance>5a842a9f5d1b5a10aa5e27a08e4bccd4</scan_instance>
        <scan_source>scan</scan_source>
        <source_id>a3a29f2afbed9a90c04cfbac7befdc25</source_id>
        <sys_class_name>sys_app_scan_variable</sys_class_name>
        <sys_created_by>john.spirko</sys_created_by>
        <sys_created_on>2025-01-18 00:37:08</sys_created_on>
        <sys_id>c7fd7fd3e7c79650d6acb05bf05068d8</sys_id>
        <sys_mod_count>1</sys_mod_count>
        <sys_name>sys_id_5025</sys_name>
        <sys_package display_value="Social Program Support - Pub Sector" source="x_snc_hhs_progra_2">acb2df2afbed9a90c04cfbac7befdc2e</sys_package>
        <sys_policy/>
        <sys_scope display_value="Social Program Support - Pub Sector">acb2df2afbed9a90c04cfbac7befdc2e</sys_scope>
        <sys_update_name>sys_app_scan_variable_c7fd7fd3e7c79650d6acb05bf05068d8</sys_update_name>
        <sys_updated_by>john.spirko</sys_updated_by>
        <sys_updated_on>2025-01-30 04:38:15</sys_updated_on>
        <template_execution_script/>
        <type display_value="Reference">242d82a65bea101001fb0c370581c7ea</type>
        <variable_hash>c41dbbcf85f3ea3e51a12ffc60019c5917ef9bc15031057ea27f079d4ffa65ce</variable_hash>
    </sys_app_scan_variable>
    <sys_update_version action="INSERT_OR_UPDATE">
        <action>DELETE</action>
        <application display_value="Social Program Support - Pub Sector">acb2df2afbed9a90c04cfbac7befdc2e</application>
        <file_path/>
        <instance_id>efeaa946dbc0c740b2e05d00cf96194a</instance_id>
        <instance_name>empjspirkosc2</instance_name>
        <name>sys_app_scan_variable_c7fd7fd3e7c79650d6acb05bf05068d8</name>
        <payload><![CDATA[<?xml version="1.0" encoding="UTF-8"?><record_update table="sys_app_scan_variable"><sys_app_scan_variable action="INSERT_OR_UPDATE"><name>sys_id_5025</name><original_value>cca1a2c33ccfd65040144ff95a45d483</original_value><referenced_table>sys_app</referenced_table><run_script>false</run_script><scan_instance>5a842a9f5d1b5a10aa5e27a08e4bccd4</scan_instance><scan_source>scan</scan_source><source_id>a3a29f2afbed9a90c04cfbac7befdc25</source_id><sys_class_name>sys_app_scan_variable</sys_class_name><sys_created_by>john.spirko</sys_created_by><sys_created_on>2025-01-18 00:37:08</sys_created_on><sys_id>c7fd7fd3e7c79650d6acb05bf05068d8</sys_id><sys_mod_count>1</sys_mod_count><sys_name>sys_id_5025</sys_name><sys_package display_value="Social Program Support - Pub Sector" source="x_snc_hhs_progra_2">acb2df2afbed9a90c04cfbac7befdc2e</sys_package><sys_policy/><sys_scope display_value="Social Program Support - Pub Sector">acb2df2afbed9a90c04cfbac7befdc2e</sys_scope><sys_update_name>sys_app_scan_variable_c7fd7fd3e7c79650d6acb05bf05068d8</sys_update_name><sys_updated_by>john.spirko</sys_updated_by><sys_updated_on>2025-01-30 04:38:15</sys_updated_on><template_execution_script/><type display_value="Reference">242d82a65bea101001fb0c370581c7ea</type><variable_hash>c41dbbcf85f3ea3e51a12ffc60019c5917ef9bc15031057ea27f079d4ffa65ce</variable_hash></sys_app_scan_variable></record_update>]]></payload>
        <payload_hash>-1618944555</payload_hash>
        <record_name>sys_id_5025</record_name>
        <reverted_from/>
        <source>8a9481db93ad9e90d6aabe8d1dba103a</source>
        <source_table>sys_update_set</source_table>
        <state>previous</state>
        <sys_created_by>john.spirko</sys_created_by>
        <sys_created_on>2025-01-30 04:38:15</sys_created_on>
        <sys_id>cc486a97fb9b5a10625bf7704eefdc56</sys_id>
        <sys_mod_count>0</sys_mod_count>
        <sys_recorded_at>194b580aa390000001</sys_recorded_at>
        <sys_updated_by>john.spirko</sys_updated_by>
        <sys_updated_on>2025-01-30 04:38:15</sys_updated_on>
        <type>Variable</type>
        <update_guid>0c486a974a9b5a10e671a1a053862349</update_guid>
        <update_guid_history>0c486a974a9b5a10e671a1a053862349:-1618944555,c7fd7fd3cac796501c7c66115827cad9:1052605312</update_guid_history>
    </sys_update_version>
    <sys_metadata_delete action="INSERT_OR_UPDATE">
        <sys_audit_delete/>
        <sys_class_name>sys_metadata_delete</sys_class_name>
        <sys_created_by>john.spirko</sys_created_by>
        <sys_created_on>2025-01-30 05:36:42</sys_created_on>
        <sys_db_object display_value="" name="sys_app_scan_variable">sys_app_scan_variable</sys_db_object>
        <sys_id>3cbd14a3463943f79eff3099d62bcfa1</sys_id>
        <sys_metadata>c7fd7fd3e7c79650d6acb05bf05068d8</sys_metadata>
        <sys_mod_count>0</sys_mod_count>
        <sys_name>sys_id_5025</sys_name>
        <sys_package display_value="Social Program Support - Pub Sector" source="x_snc_hhs_progra_2">acb2df2afbed9a90c04cfbac7befdc2e</sys_package>
        <sys_parent/>
        <sys_policy/>
        <sys_scope display_value="Social Program Support - Pub Sector">acb2df2afbed9a90c04cfbac7befdc2e</sys_scope>
        <sys_scope_delete display_value="">3193c3af00d14183a2bae770b8670da1</sys_scope_delete>
        <sys_update_name>sys_app_scan_variable_c7fd7fd3e7c79650d6acb05bf05068d8</sys_update_name>
        <sys_update_version display_value="sys_app_scan_variable_c7fd7fd3e7c79650d6acb05bf05068d8">cc486a97fb9b5a10625bf7704eefdc56</sys_update_version>
        <sys_updated_by>john.spirko</sys_updated_by>
        <sys_updated_on>2025-01-30 05:36:42</sys_updated_on>
    </sys_metadata_delete>
</record_update>
