<?xml version="1.0" encoding="UTF-8"?><record_update table="sys_app_scan_variable">
    <sys_app_scan_variable action="DELETE">
        <name>sys_id_22577</name>
        <original_value>6c6ca8f1f45b5610c3358812f396182c</original_value>
        <referenced_table>sys_app</referenced_table>
        <run_script>false</run_script>
        <scan_instance>5a842a9f5d1b5a10aa5e27a08e4bccd4</scan_instance>
        <scan_source>scan</scan_source>
        <source_id>a3a29f2afbed9a90c04cfbac7befdc25</source_id>
        <sys_class_name>sys_app_scan_variable</sys_class_name>
        <sys_created_by>john.spirko</sys_created_by>
        <sys_created_on>2025-01-30 04:53:40</sys_created_on>
        <sys_id>c6cb2e5f6ddb5a10a8c6669d46cbdd7d</sys_id>
        <sys_mod_count>0</sys_mod_count>
        <sys_name>sys_id_22577</sys_name>
        <sys_package display_value="Social Program Support - Pub Sector" source="x_snc_hhs_progra_2">acb2df2afbed9a90c04cfbac7befdc2e</sys_package>
        <sys_policy/>
        <sys_scope display_value="Social Program Support - Pub Sector">acb2df2afbed9a90c04cfbac7befdc2e</sys_scope>
        <sys_update_name>sys_app_scan_variable_c6cb2e5f6ddb5a10a8c6669d46cbdd7d</sys_update_name>
        <sys_updated_by>john.spirko</sys_updated_by>
        <sys_updated_on>2025-01-30 04:53:40</sys_updated_on>
        <template_execution_script/>
        <type display_value="Reference">242d82a65bea101001fb0c370581c7ea</type>
        <variable_hash>d9a90c4f83714dbabd097195712bf27ca009927da368e0d632510aa7951d3871</variable_hash>
    </sys_app_scan_variable>
    <sys_update_version action="INSERT_OR_UPDATE">
        <action>DELETE</action>
        <application display_value="Social Program Support - Pub Sector">acb2df2afbed9a90c04cfbac7befdc2e</application>
        <file_path/>
        <instance_id>efeaa946dbc0c740b2e05d00cf96194a</instance_id>
        <instance_name>empjspirkosc2</instance_name>
        <name>sys_app_scan_variable_c6cb2e5f6ddb5a10a8c6669d46cbdd7d</name>
        <payload><![CDATA[<?xml version="1.0" encoding="UTF-8"?><record_update table="sys_app_scan_variable"><sys_app_scan_variable action="INSERT_OR_UPDATE"><name>sys_id_22577</name><original_value>6c6ca8f1f45b5610c3358812f396182c</original_value><referenced_table>sys_app</referenced_table><run_script>false</run_script><scan_instance>5a842a9f5d1b5a10aa5e27a08e4bccd4</scan_instance><scan_source>scan</scan_source><source_id>a3a29f2afbed9a90c04cfbac7befdc25</source_id><sys_class_name>sys_app_scan_variable</sys_class_name><sys_created_by>john.spirko</sys_created_by><sys_created_on>2025-01-30 04:53:40</sys_created_on><sys_id>c6cb2e5f6ddb5a10a8c6669d46cbdd7d</sys_id><sys_mod_count>0</sys_mod_count><sys_name>sys_id_22577</sys_name><sys_package display_value="Social Program Support - Pub Sector" source="x_snc_hhs_progra_2">acb2df2afbed9a90c04cfbac7befdc2e</sys_package><sys_policy/><sys_scope display_value="Social Program Support - Pub Sector">acb2df2afbed9a90c04cfbac7befdc2e</sys_scope><sys_update_name>sys_app_scan_variable_c6cb2e5f6ddb5a10a8c6669d46cbdd7d</sys_update_name><sys_updated_by>john.spirko</sys_updated_by><sys_updated_on>2025-01-30 04:53:40</sys_updated_on><template_execution_script/><type display_value="Reference">242d82a65bea101001fb0c370581c7ea</type><variable_hash>d9a90c4f83714dbabd097195712bf27ca009927da368e0d632510aa7951d3871</variable_hash></sys_app_scan_variable></record_update>]]></payload>
        <payload_hash>639343357</payload_hash>
        <record_name>sys_id_22577</record_name>
        <reverted_from/>
        <source>8a9481db93ad9e90d6aabe8d1dba103a</source>
        <source_table>sys_update_set</source_table>
        <state>previous</state>
        <sys_created_by>john.spirko</sys_created_by>
        <sys_created_on>2025-01-30 04:53:40</sys_created_on>
        <sys_id>06cb2e5ffbdb5a10625bf7704eefdc7f</sys_id>
        <sys_mod_count>0</sys_mod_count>
        <sys_recorded_at>194b58ec7d20000001</sys_recorded_at>
        <sys_updated_by>john.spirko</sys_updated_by>
        <sys_updated_on>2025-01-30 04:53:40</sys_updated_on>
        <type>Variable</type>
        <update_guid>c6cb2e5f40db5a10b4e8194ef29f857e</update_guid>
        <update_guid_history>c6cb2e5f40db5a10b4e8194ef29f857e:639343357</update_guid_history>
    </sys_update_version>
    <sys_metadata_delete action="INSERT_OR_UPDATE">
        <sys_audit_delete/>
        <sys_class_name>sys_metadata_delete</sys_class_name>
        <sys_created_by>john.spirko</sys_created_by>
        <sys_created_on>2025-01-30 05:36:33</sys_created_on>
        <sys_db_object display_value="" name="sys_app_scan_variable">sys_app_scan_variable</sys_db_object>
        <sys_id>8e827dc0166348f5965c16134d571f11</sys_id>
        <sys_metadata>c6cb2e5f6ddb5a10a8c6669d46cbdd7d</sys_metadata>
        <sys_mod_count>0</sys_mod_count>
        <sys_name>sys_id_22577</sys_name>
        <sys_package display_value="Social Program Support - Pub Sector" source="x_snc_hhs_progra_2">acb2df2afbed9a90c04cfbac7befdc2e</sys_package>
        <sys_parent/>
        <sys_policy/>
        <sys_scope display_value="Social Program Support - Pub Sector">acb2df2afbed9a90c04cfbac7befdc2e</sys_scope>
        <sys_scope_delete display_value="">3193c3af00d14183a2bae770b8670da1</sys_scope_delete>
        <sys_update_name>sys_app_scan_variable_c6cb2e5f6ddb5a10a8c6669d46cbdd7d</sys_update_name>
        <sys_update_version display_value="sys_app_scan_variable_c6cb2e5f6ddb5a10a8c6669d46cbdd7d">06cb2e5ffbdb5a10625bf7704eefdc7f</sys_update_version>
        <sys_updated_by>john.spirko</sys_updated_by>
        <sys_updated_on>2025-01-30 05:36:33</sys_updated_on>
    </sys_metadata_delete>
</record_update>
