<?xml version="1.0" encoding="UTF-8"?><record_update table="sys_app_scan_variable">
    <sys_app_scan_variable action="DELETE">
        <name>sys_id_35</name>
        <original_value>8b4aa4fefb29da90c04cfbac7befdca0</original_value>
        <referenced_table>sys_app</referenced_table>
        <run_script>false</run_script>
        <scan_instance>927931909fa7121008deb63ecc4feb58</scan_instance>
        <scan_source>scan</scan_source>
        <source_id>a3a29f2afbed9a90c04cfbac7befdc25</source_id>
        <sys_class_name>sys_app_scan_variable</sys_class_name>
        <sys_created_by>john.spirko</sys_created_by>
        <sys_created_on>2024-11-02 20:51:36</sys_created_on>
        <sys_id>da813ff2d0ad1e90ac40b23bbbfd6e46</sys_id>
        <sys_mod_count>10</sys_mod_count>
        <sys_name>sys_id_35</sys_name>
        <sys_package display_value="Social Program Support - Pub Sector" source="x_snc_hhs_progra_2">acb2df2afbed9a90c04cfbac7befdc2e</sys_package>
        <sys_policy/>
        <sys_scope display_value="Social Program Support - Pub Sector">acb2df2afbed9a90c04cfbac7befdc2e</sys_scope>
        <sys_update_name>sys_app_scan_variable_da813ff2d0ad1e90ac40b23bbbfd6e46</sys_update_name>
        <sys_updated_by>john.spirko</sys_updated_by>
        <sys_updated_on>2025-02-02 03:48:12</sys_updated_on>
        <template_execution_script/>
        <type display_value="Reference">242d82a65bea101001fb0c370581c7ea</type>
        <variable_hash>609e2d0704b242f7cca4851903c2db3630897d912e0eddeb03c2cd5014b205c5</variable_hash>
    </sys_app_scan_variable>
    <sys_update_version action="INSERT_OR_UPDATE">
        <action>DELETE</action>
        <application display_value="Social Program Support - Pub Sector">acb2df2afbed9a90c04cfbac7befdc2e</application>
        <file_path/>
        <instance_id>efeaa946dbc0c740b2e05d00cf96194a</instance_id>
        <instance_name>empjspirkosc2</instance_name>
        <name>sys_app_scan_variable_da813ff2d0ad1e90ac40b23bbbfd6e46</name>
        <payload><![CDATA[<?xml version="1.0" encoding="UTF-8"?><record_update table="sys_app_scan_variable"><sys_app_scan_variable action="INSERT_OR_UPDATE"><name>sys_id_35</name><original_value>8b4aa4fefb29da90c04cfbac7befdca0</original_value><referenced_table>sys_app</referenced_table><run_script>false</run_script><scan_instance>927931909fa7121008deb63ecc4feb58</scan_instance><scan_source>scan</scan_source><source_id>a3a29f2afbed9a90c04cfbac7befdc25</source_id><sys_class_name>sys_app_scan_variable</sys_class_name><sys_created_by>john.spirko</sys_created_by><sys_created_on>2024-11-02 20:51:36</sys_created_on><sys_id>da813ff2d0ad1e90ac40b23bbbfd6e46</sys_id><sys_mod_count>10</sys_mod_count><sys_name>sys_id_35</sys_name><sys_package display_value="Social Program Support - Pub Sector" source="x_snc_hhs_progra_2">acb2df2afbed9a90c04cfbac7befdc2e</sys_package><sys_policy/><sys_scope display_value="Social Program Support - Pub Sector">acb2df2afbed9a90c04cfbac7befdc2e</sys_scope><sys_update_name>sys_app_scan_variable_da813ff2d0ad1e90ac40b23bbbfd6e46</sys_update_name><sys_updated_by>john.spirko</sys_updated_by><sys_updated_on>2025-02-02 03:48:12</sys_updated_on><template_execution_script/><type display_value="Reference">242d82a65bea101001fb0c370581c7ea</type><variable_hash>609e2d0704b242f7cca4851903c2db3630897d912e0eddeb03c2cd5014b205c5</variable_hash></sys_app_scan_variable></record_update>]]></payload>
        <payload_hash>-2044966520</payload_hash>
        <record_name>sys_id_35</record_name>
        <reverted_from/>
        <source>8a9481db93ad9e90d6aabe8d1dba103a</source>
        <source_table>sys_update_set</source_table>
        <state>previous</state>
        <sys_created_by>john.spirko</sys_created_by>
        <sys_created_on>2025-02-02 03:48:12</sys_created_on>
        <sys_id>94997990fba71210c04cfbac7befdc0f</sys_id>
        <sys_mod_count>0</sys_mod_count>
        <sys_recorded_at>194c4c5e9cc0000001</sys_recorded_at>
        <sys_updated_by>john.spirko</sys_updated_by>
        <sys_updated_on>2025-02-02 03:48:12</sys_updated_on>
        <type>Variable</type>
        <update_guid>98997990aaa7121017a4b6cd1662a50e</update_guid>
        <update_guid_history>98997990aaa7121017a4b6cd1662a50e:-2044966520,1de1ab8c4befde1094f2cbb69ce39695:871425078,f46e6a536e5f5a10e4491cd81ca0b5fa:166574600,5ba46adfdf1b5a10d1690e0808a19127:1899460818,ebec739b22879650306238732113b9f2:16991647,7b690f56913a96d0e59ece301f2204e9:1654204611,fecaffa8cfbe1e905e69a93dec3dc27b:294478466,f140ab6450fa1e90ce2806e3f54e0eb0:402421789,923c6e1f74a9de9030c272a14d53e0af:1655616972,9a42c9d3bdad9e90784b7bc02c252793:1807351000,da813ff2abad1e9087d9d540ef7cbf47:-98500706</update_guid_history>
    </sys_update_version>
    <sys_metadata_delete action="INSERT_OR_UPDATE">
        <sys_audit_delete/>
        <sys_class_name>sys_metadata_delete</sys_class_name>
        <sys_created_by>john.spirko</sys_created_by>
        <sys_created_on>2025-02-03 03:49:15</sys_created_on>
        <sys_db_object display_value="" name="sys_app_scan_variable">sys_app_scan_variable</sys_db_object>
        <sys_id>120f63b308b34eb09f8937f4df6a3b10</sys_id>
        <sys_metadata>da813ff2d0ad1e90ac40b23bbbfd6e46</sys_metadata>
        <sys_mod_count>0</sys_mod_count>
        <sys_name>sys_id_35</sys_name>
        <sys_package display_value="Social Program Support - Pub Sector" source="x_snc_hhs_progra_2">acb2df2afbed9a90c04cfbac7befdc2e</sys_package>
        <sys_parent/>
        <sys_policy/>
        <sys_scope display_value="Social Program Support - Pub Sector">acb2df2afbed9a90c04cfbac7befdc2e</sys_scope>
        <sys_scope_delete display_value="">3193c3af00d14183a2bae770b8670da1</sys_scope_delete>
        <sys_update_name>sys_app_scan_variable_da813ff2d0ad1e90ac40b23bbbfd6e46</sys_update_name>
        <sys_update_version display_value="sys_app_scan_variable_da813ff2d0ad1e90ac40b23bbbfd6e46">94997990fba71210c04cfbac7befdc0f</sys_update_version>
        <sys_updated_by>john.spirko</sys_updated_by>
        <sys_updated_on>2025-02-03 03:49:15</sys_updated_on>
    </sys_metadata_delete>
</record_update>
