<?xml version="1.0" encoding="UTF-8"?><record_update table="sys_app_scan_variable">
    <sys_app_scan_variable action="DELETE">
        <name>sys_id_20595</name>
        <original_value>ecdcdc399dd7561020dd0fa2a8b1e7bb</original_value>
        <referenced_table>sys_app</referenced_table>
        <run_script>false</run_script>
        <scan_instance>5a842a9f5d1b5a10aa5e27a08e4bccd4</scan_instance>
        <scan_source>scan</scan_source>
        <source_id>a3a29f2afbed9a90c04cfbac7befdc25</source_id>
        <sys_class_name>sys_app_scan_variable</sys_class_name>
        <sys_created_by>john.spirko</sys_created_by>
        <sys_created_on>2025-01-30 04:49:07</sys_created_on>
        <sys_id>57baa6d797db5a10110c4fcb7cd90f01</sys_id>
        <sys_mod_count>0</sys_mod_count>
        <sys_name>sys_id_20595</sys_name>
        <sys_package display_value="Social Program Support - Pub Sector" source="x_snc_hhs_progra_2">acb2df2afbed9a90c04cfbac7befdc2e</sys_package>
        <sys_policy/>
        <sys_scope display_value="Social Program Support - Pub Sector">acb2df2afbed9a90c04cfbac7befdc2e</sys_scope>
        <sys_update_name>sys_app_scan_variable_57baa6d797db5a10110c4fcb7cd90f01</sys_update_name>
        <sys_updated_by>john.spirko</sys_updated_by>
        <sys_updated_on>2025-01-30 04:49:07</sys_updated_on>
        <template_execution_script/>
        <type display_value="Reference">242d82a65bea101001fb0c370581c7ea</type>
        <variable_hash>39572a95894488f0eeea7bddc2b6e260429da12d0c5bac93707677c2c15b5be0</variable_hash>
    </sys_app_scan_variable>
    <sys_update_version action="INSERT_OR_UPDATE">
        <action>DELETE</action>
        <application display_value="Social Program Support - Pub Sector">acb2df2afbed9a90c04cfbac7befdc2e</application>
        <file_path/>
        <instance_id>efeaa946dbc0c740b2e05d00cf96194a</instance_id>
        <instance_name>empjspirkosc2</instance_name>
        <name>sys_app_scan_variable_57baa6d797db5a10110c4fcb7cd90f01</name>
        <payload><![CDATA[<?xml version="1.0" encoding="UTF-8"?><record_update table="sys_app_scan_variable"><sys_app_scan_variable action="INSERT_OR_UPDATE"><name>sys_id_20595</name><original_value>ecdcdc399dd7561020dd0fa2a8b1e7bb</original_value><referenced_table>sys_app</referenced_table><run_script>false</run_script><scan_instance>5a842a9f5d1b5a10aa5e27a08e4bccd4</scan_instance><scan_source>scan</scan_source><source_id>a3a29f2afbed9a90c04cfbac7befdc25</source_id><sys_class_name>sys_app_scan_variable</sys_class_name><sys_created_by>john.spirko</sys_created_by><sys_created_on>2025-01-30 04:49:07</sys_created_on><sys_id>57baa6d797db5a10110c4fcb7cd90f01</sys_id><sys_mod_count>0</sys_mod_count><sys_name>sys_id_20595</sys_name><sys_package display_value="Social Program Support - Pub Sector" source="x_snc_hhs_progra_2">acb2df2afbed9a90c04cfbac7befdc2e</sys_package><sys_policy/><sys_scope display_value="Social Program Support - Pub Sector">acb2df2afbed9a90c04cfbac7befdc2e</sys_scope><sys_update_name>sys_app_scan_variable_57baa6d797db5a10110c4fcb7cd90f01</sys_update_name><sys_updated_by>john.spirko</sys_updated_by><sys_updated_on>2025-01-30 04:49:07</sys_updated_on><template_execution_script/><type display_value="Reference">242d82a65bea101001fb0c370581c7ea</type><variable_hash>39572a95894488f0eeea7bddc2b6e260429da12d0c5bac93707677c2c15b5be0</variable_hash></sys_app_scan_variable></record_update>]]></payload>
        <payload_hash>-817936380</payload_hash>
        <record_name>sys_id_20595</record_name>
        <reverted_from/>
        <source>8a9481db93ad9e90d6aabe8d1dba103a</source>
        <source_table>sys_update_set</source_table>
        <state>previous</state>
        <sys_created_by>john.spirko</sys_created_by>
        <sys_created_on>2025-01-30 04:49:07</sys_created_on>
        <sys_id>9bbaa6d7fbdb5a10625bf7704eefdc0f</sys_id>
        <sys_mod_count>0</sys_mod_count>
        <sys_recorded_at>194b58a9b900000001</sys_recorded_at>
        <sys_updated_by>john.spirko</sys_updated_by>
        <sys_updated_on>2025-01-30 04:49:07</sys_updated_on>
        <type>Variable</type>
        <update_guid>5fbaa6d7dedb5a101ea598c87a21400e</update_guid>
        <update_guid_history>5fbaa6d7dedb5a101ea598c87a21400e:-817936380</update_guid_history>
    </sys_update_version>
    <sys_metadata_delete action="INSERT_OR_UPDATE">
        <sys_audit_delete/>
        <sys_class_name>sys_metadata_delete</sys_class_name>
        <sys_created_by>john.spirko</sys_created_by>
        <sys_created_on>2025-01-30 05:21:24</sys_created_on>
        <sys_db_object display_value="" name="sys_app_scan_variable">sys_app_scan_variable</sys_db_object>
        <sys_id>2d3e7e11415c4b64b2b637500fc225e4</sys_id>
        <sys_metadata>57baa6d797db5a10110c4fcb7cd90f01</sys_metadata>
        <sys_mod_count>0</sys_mod_count>
        <sys_name>sys_id_20595</sys_name>
        <sys_package display_value="Social Program Support - Pub Sector" source="x_snc_hhs_progra_2">acb2df2afbed9a90c04cfbac7befdc2e</sys_package>
        <sys_parent/>
        <sys_policy/>
        <sys_scope display_value="Social Program Support - Pub Sector">acb2df2afbed9a90c04cfbac7befdc2e</sys_scope>
        <sys_scope_delete display_value="">3193c3af00d14183a2bae770b8670da1</sys_scope_delete>
        <sys_update_name>sys_app_scan_variable_57baa6d797db5a10110c4fcb7cd90f01</sys_update_name>
        <sys_update_version display_value="sys_app_scan_variable_57baa6d797db5a10110c4fcb7cd90f01">9bbaa6d7fbdb5a10625bf7704eefdc0f</sys_update_version>
        <sys_updated_by>john.spirko</sys_updated_by>
        <sys_updated_on>2025-01-30 05:21:24</sys_updated_on>
    </sys_metadata_delete>
</record_update>
